cellmachine/__init__.py
cellmachine/cells/__init__.py
cellmachine/cells/ccw.py
cellmachine/cells/cell.py
cellmachine/cells/cw.py
cellmachine/cells/enemy.py
cellmachine/cells/generator.py
cellmachine/cells/immobile.py
cellmachine/cells/mover.py
cellmachine/cells/push.py
cellmachine/cells/slide.py
cellmachine/cells/trash.py
cellmachine/level.py
cellmachine/levelstring/__init__.py
cellmachine/levelstring/v1.py
cellmachine/levelstring/v2.py
cellmachine/levelstring/v3.py
cellmachine/textures/.DS_Store
cellmachine/textures/0.png
cellmachine/textures/BGDefault.png
cellmachine/textures/ccw.png
cellmachine/textures/cw.png
cellmachine/textures/enemy.png
cellmachine/textures/generator.png
cellmachine/textures/immobile.png
cellmachine/textures/mover.png
cellmachine/textures/push.png
cellmachine/textures/slide.png
cellmachine/textures/trash.png
cellmachine-1.3.3.dist-info/LICENSE
cellmachine-1.3.3.dist-info/METADATA
cellmachine-1.3.3.dist-info/WHEEL
cellmachine-1.3.3.dist-info/RECORD
