Metadata-Version: 2.1
Name: cellmachine
Version: 1.3.3
Summary: All things Cell Machine.
Author: kegnh
Author-email: itskegnh@gmail.com
Requires-Python: >=3.9,<4.0
Classifier: Programming Language :: Python :: 3
Classifier: Programming Language :: Python :: 3.9
Classifier: Programming Language :: Python :: 3.10
Classifier: Programming Language :: Python :: 3.11
